simple_ocio/__init__.py
simple_ocio/tone_mapper.py
simple_ocio/ocio_data/config.ocio
simple_ocio/ocio_data/ocio-license.txt
simple_ocio/ocio_data/filmic/filmic_desat_33.cube
simple_ocio/ocio_data/filmic/filmic_to_0-35_1-30.spi1d
simple_ocio/ocio_data/filmic/filmic_to_0-48_1-09.spi1d
simple_ocio/ocio_data/filmic/filmic_to_0-60_1-04.spi1d
simple_ocio/ocio_data/filmic/filmic_to_0-70_1-03.spi1d
simple_ocio/ocio_data/filmic/filmic_to_0-85_1-011.spi1d
simple_ocio/ocio_data/filmic/filmic_to_0.99_1-0075.spi1d
simple_ocio/ocio_data/filmic/filmic_to_1.20_1-00.spi1d
simple_ocio/ocio_data/luts/AgX_Base_P3.cube
simple_ocio/ocio_data/luts/AgX_Base_Rec2020.cube
simple_ocio/ocio_data/luts/AgX_Base_sRGB.cube
simple_ocio/ocio_data/luts/AgX_False_Color.spi1d
simple_ocio/ocio_data/luts/Guard_Rail_Shaper_EOTF.spi1d
simple_ocio/ocio_data/luts/Inverse_AgX_Base_Rec2020.cube
simple_ocio/ocio_data/luts/luminance_compensation_bt2020.cube
simple_ocio/ocio_data/luts/luminance_compensation_p3.cube
simple_ocio/ocio_data/luts/luminance_compensation_srgb.cube
simple_ocio/ocio_data/luts/pbrNeutral.cube
simple_ocio/ocio_data/luts/xyz_E_to_D65.spimtx
simple_ocio-0.2.0.dist-info/licenses/LICENSE
simple_ocio-0.2.0.dist-info/METADATA
simple_ocio-0.2.0.dist-info/WHEEL
simple_ocio-0.2.0.dist-info/top_level.txt
simple_ocio-0.2.0.dist-info/RECORD
