Metadata-Version: 2.4
Name: simple-ocio
Version: 0.2.0
Summary: Simple NumPy-first OpenColorIO Tone-mapping Toolkit
Author-email: NCJ <me@ncj.wiki>
License: MIT
Project-URL: Source, https://github.com/iamNCJ/simple-ocio
Requires-Python: >=3.8
License-File: LICENSE
Requires-Dist: numpy>=1.22
Requires-Dist: opencolorio>=2
Dynamic: license-file
